at89overlord/__init__.py
at89overlord/at89comm.py
at89overlord/at89runner.py
at89overlord-0.4.0.dist-info/METADATA
at89overlord-0.4.0.dist-info/RECORD
at89overlord-0.4.0.dist-info/WHEEL
at89overlord-0.4.0.dist-info/entry_points.txt
at89overlord-0.4.0.dist-info/top_level.txt
