Metadata-Version: 2.1
Name: at89overlord
Version: 0.4.0
Summary: Arduino-based AT89C2051 programmer
Home-page: https://github.com/piotrb5e3/AT89C2051_programmer
Author: Piotr Bakalarski
Author-email: piotrb5e3@gmail.com
License: GPLv3
Platform: UNKNOWN
Classifier: Development Status :: 3 - Alpha
Classifier: Intended Audience :: Developers
Classifier: Intended Audience :: Education
Classifier: Topic :: Software Development :: Embedded Systems
Classifier: License :: OSI Approved :: GNU General Public License v3 (GPLv3)
Classifier: Environment :: Console
Classifier: Operating System :: MacOS :: MacOS X
Classifier: Operating System :: Microsoft :: Windows
Classifier: Operating System :: POSIX
Classifier: Programming Language :: Python :: 3
Classifier: Programming Language :: Python :: 3.5
Classifier: Programming Language :: Python :: 3.6
Requires-Python: >=3.5
Requires-Dist: intelhex
Requires-Dist: pyserial
Requires-Dist: termcolor
